pgn_read/__init__.py
pgn_read/core/__init__.py
pgn_read/core/constants.py
pgn_read/core/game.py
pgn_read/core/game_ignore_case_pgn.py
pgn_read/core/game_indicate_check.py
pgn_read/core/game_strict_pgn.py
pgn_read/core/game_text_pgn.py
pgn_read/core/gamedata.py
pgn_read/core/movetext_parser.py
pgn_read/core/parser.py
pgn_read/core/piece.py
pgn_read/core/squares.py
pgn_read/core/tagpair_parser.py
pgn_read/samples/_utilities.py
pgn_read/samples/_utilities_moves.py
pgn_read/samples/_utilities_tagpair.py
pgn_read/samples/count_games.py
pgn_read/samples/count_tag_pairs.py
pgn_read/samples/ignore_case_pgn_games.py
pgn_read/samples/pgn_games.py
pgn_read/samples/strict_pgn_games.py
pgn_read/samples/text_pgn_games.py
pgn_read-2.6.dist-info/licenses/LICENCE
pgn_read-2.6.dist-info/METADATA
pgn_read-2.6.dist-info/WHEEL
pgn_read-2.6.dist-info/top_level.txt
pgn_read-2.6.dist-info/RECORD
