Metadata-Version: 2.4
Name: pgn-read
Version: 2.6
Summary: Portable Game Notation (PGN) parser.
Author-email: Roger Marsh <roger.marsh@solentware.co.uk>
License-Expression: BSD-3-Clause
Project-URL: Homepage, http://www.solentware.co.uk
Project-URL: Repository, https://github.com/RogerMarsh/pgn-read.git
Project-URL: Bug Tracker, https://github.com/RogerMarsh/pgn-read/issues
Classifier: Programming Language :: Python :: 3.7
Classifier: Programming Language :: Python :: 3.8
Classifier: Programming Language :: Python :: 3.9
Classifier: Programming Language :: Python :: 3.10
Classifier: Programming Language :: Python :: 3.11
Classifier: Operating System :: OS Independent
Classifier: Topic :: Software Development
Classifier: Topic :: Games/Entertainment :: Board Games
Classifier: Intended Audience :: Developers
Classifier: Development Status :: 3 - Alpha
License-File: LICENCE
Dynamic: license-file
